dw_python_monetdb_async-12.0.2.dist-info/METADATA
dw_python_monetdb_async-12.0.2.dist-info/RECORD
dw_python_monetdb_async-12.0.2.dist-info/WHEEL
dw_python_monetdb_async-12.0.2.dist-info/top_level.txt
monetdb/__init__.py
monetdb/control.py
monetdb/exceptions.py
monetdb/mapi.py
monetdb/sql/__init__.py
monetdb/sql/connections.py
monetdb/sql/converters.py
monetdb/sql/cursors.py
monetdb/sql/monetize.py
monetdb/sql/pythonize.py
monetdb/sql/types.py
