Metadata-Version: 2.1
Name: dw-python-monetdb-async
Version: 12.0.2
Summary: Native MonetDB client Python API
Home-page: http://www.monetdb.org/
Author: MonetDB BV
Author-email: info@monetdb.org
License: UNKNOWN
Download-URL: http://dev.monetdb.org/downloads/sources/Oct2014-SP2/python3-monetdb-11.19.9.tar.gz
Platform: UNKNOWN
Classifier: Topic :: Database
Classifier: Topic :: Database :: Database Engines/Servers
Classifier: Development Status :: 5 - Production/Stable
Classifier: Intended Audience :: Developers
Classifier: License :: Other/Proprietary License
Requires-Dist: greenlet (==0.4.14)
